README.rst
setup.py
anduin/Scheduler.py
anduin/__init__.py
anduin/construct_file.py
anduin/server.py
anduin/dbserver/base.py
anduin/dbserver/data_manager.py
anduindata.egg-info/PKG-INFO
anduindata.egg-info/SOURCES.txt
anduindata.egg-info/dependency_links.txt
anduindata.egg-info/requires.txt
anduindata.egg-info/top_level.txt
anduindata.egg-info/zip-safe