Metadata-Version: 1.2
Name: anduindata
Version: 1.3.1
Summary: a mysql connector
Home-page: https://github.com/campanulamediuml/Anduin
Author: campanula
Author-email: 421248329@qq.com
License: MIT
Keywords: mysql
Platform: any
Classifier: License :: OSI Approved :: MIT License
Classifier: Intended Audience :: Developers
Classifier: Operating System :: OS Independent
Classifier: Programming Language :: Python :: 3
Requires-Python: >=3.2
